{
  "hash": "3fc2d592faf5d4eaa3ff81c531be1ee8",
  "result": {
    "markdown": "---\ndescription: \"TemplateEN, TemplateTR, patoloji, atlas, pathology, whole slide image templateTR\"\ndate: last-modified\ncategories: [template]\npage-layout: full\nbibliography: references.bib\n---\n\n::: {.cell}\n\n:::\n\n::: {.cell}\n# Mide Patolojisi {#sec-mide-patolojisi} \n:::\n\n::: {.cell}\n\n:::\n\n::: {.cell}\n## Gastritis Cystica Profunda {#sec-gastritis-cystica-profunda} \n:::\n\n::: {.cell}\n\n:::\n\n\n\n::: {.cell}\n\n**Gastritis Cystica Profunda**\n\n\n[![Tam Ekran Görmek İçin Resmi Tıklayın](./screenshots/gastritis-cystica-profunda_screenshot.png){width=\"25%\"}](https://images.patolojiatlasi.com/gastritis-cystica-profunda/HE.html) [Tam Ekran Görmek İçin Resmi Tıklayın](https://images.patolojiatlasi.com/gastritis-cystica-profunda/HE.html)\n:::\n\n::: {.cell}\n\nMikroskopik görüntüleri inceleyin:\n\n<iframe src=\"https://images.patolojiatlasi.com/gastritis-cystica-profunda/HE.html\" style=\"height:600px;width:100%;\" data-external=\"1\"></iframe>\n:::\n\n::: {.cell}\n\n:::\n\n::: {.cell}\n\n:::\n",
    "supporting": [
      "mide_files"
    ],
    "filters": [
      "rmarkdown/pagebreak.lua"
    ],
    "includes": {},
    "engineDependencies": {},
    "preserve": {},
    "postProcess": true
  }
}