{
  "hash": "630cdcd24f8d4e1dbd576fa9f53ebea0",
  "result": {
    "markdown": "---\ndescription: |\n    congestion in spleen\n    dalak konjesyon\ndate: last-modified\ncategories: [congestion, spleen]\npage-layout: full\nbibliography: references.bib\n---\n\n::: {.cell}\n\n:::\n\n::: {.cell}\n\n:::\n\n::: {.cell}\n## Congestion in spleen {#sec-congestion-spleen}\n:::\n\n\n\n\n\n\n\n::: {.cell}\n\n:::\n\n::: {.cell}\n\n:::\n\n\n\n\n\n\n\n\n\n::: {.cell}\n\n**Congestion in spleen**\n\n[![Click for Full Screen WSI](./screenshots/congestion-spleen_screenshot.png){width=\"25%\"}](https://images.patolojiatlasi.com/congestion-spleen/HE.html) [Click for Full Screen WSI](https://images.patolojiatlasi.com/congestion-spleen/HE.html)\n:::\n\n::: {.cell}\n\nSee Microscopy with viewer: \n\n<iframe src=\"https://images.patolojiatlasi.com/congestion-spleen/HE.html\" style=\"height:600px;width:100%;\" data-external=\"1\"></iframe>\n:::\n\n\n\n\n\n\n\n\n\n\n\n\n",
    "supporting": [
      "congestion_files"
    ],
    "filters": [
      "rmarkdown/pagebreak.lua"
    ],
    "includes": {},
    "engineDependencies": {},
    "preserve": {},
    "postProcess": true
  }
}